LICENSE
MANIFEST.in
README.rst
setup.cfg
setup.py
docs/man/genenga.1
docs/source/HISTORY.rst
docs/source/README.rst
docs/source/index.rst
docs/source/modules/index.rst
example/address.csv
example/address.tex
example/cat.jpg
example/cat.xbb
example/nenga-yoko.tex
genenga/__init__.py
genenga/command.py
genenga/control.py
genenga/convert.py
genenga/exceptions.py
genenga/models.py
genenga.egg-info/PKG-INFO
genenga.egg-info/SOURCES.txt
genenga.egg-info/dependency_links.txt
genenga.egg-info/entry_points.txt
genenga.egg-info/requires.txt
genenga.egg-info/top_level.txt
genenga/tests/__init__.py
genenga/tests/test_command.py
genenga/tests/test_control.py
genenga/tests/test_convert.py
genenga/tests/test_models.py
template/address.mustache
template/jis-cjk.map
template/jis-cjk_mochu.map
template/jis-cjk_mochu.map~
template/vlpgothic.map