Metadata-Version: 1.1
Name: genenga
Version: 0.7.0
Summary: Generate Nengajo(Japanese new year card) pdf from address list.
Home-page: https://github.com/mkouhei/GenNenga
Author: Kouhei Maeda
Author-email: mkouhei@palmtb.net
License: GNU General Public License version 3
Platform: UNKNOWN
Classifier: Development Status :: 4 - Beta
Classifier: License :: OSI Approved :: GNU General Public License v3 or later (GPLv3+)
Classifier: Intended Audience :: End Users/Desktop
Classifier: Natural Language :: Japanese
Classifier: Programming Language :: Python
Classifier: Programming Language :: Python :: 3
Classifier: Programming Language :: Python :: 3.5
Classifier: Programming Language :: Python :: 3.6
Classifier: Programming Language :: Python :: 3.7
Classifier: Programming Language :: Python :: Implementation :: CPython
Classifier: Programming Language :: Python :: Implementation :: PyPy
Classifier: Topic :: Text Processing :: Markup :: LaTeX
